requestrepo/__init__.py
requestrepo/py.typed
requestrepo/models/__init__.py
requestrepo-2.0.1.dist-info/METADATA
requestrepo-2.0.1.dist-info/WHEEL
requestrepo-2.0.1.dist-info/licenses/LICENSE
requestrepo-2.0.1.dist-info/RECORD
